ddx/.gitignore
ddx/__init__.py
ddx/_rust/__init__.pyi
ddx/_rust/common/__init__.pyi
ddx/_rust/common/accounting.pyi
ddx/_rust/common/enums.pyi
ddx/_rust/common/requests/__init__.pyi
ddx/_rust/common/requests/intents.pyi
ddx/_rust/common/specs.pyi
ddx/_rust/common/state/__init__.pyi
ddx/_rust/common/state/keys.pyi
ddx/_rust/common/transactions.pyi
ddx/_rust/decimal.pyi
ddx/_rust/h256.pyi
ddx/_rust.abi3.so
ddx/app_config/ethereum/addresses.json
ddx/auditor/README.md
ddx/auditor/__init__.py
ddx/auditor/auditor_driver.py
ddx/auditor/websocket_message.py
ddx/common/__init__.py
ddx/common/epoch_params.py
ddx/common/fill_context.py
ddx/common/logging.py
ddx/common/market_aware_account.py
ddx/common/market_specs.py
ddx/common/trade_mining_params.py
ddx/common/transaction_utils.py
ddx/common/transactions/__init__.py
ddx/common/transactions/advance_epoch.py
ddx/common/transactions/advance_settlement_epoch.py
ddx/common/transactions/all_price_checkpoints.py
ddx/common/transactions/cancel.py
ddx/common/transactions/cancel_all.py
ddx/common/transactions/complete_fill.py
ddx/common/transactions/disaster_recovery.py
ddx/common/transactions/event.py
ddx/common/transactions/fee_distribution.py
ddx/common/transactions/funding.py
ddx/common/transactions/futures_expiry.py
ddx/common/transactions/genesis.py
ddx/common/transactions/inner/__init__.py
ddx/common/transactions/inner/adl_outcome.py
ddx/common/transactions/inner/fill.py
ddx/common/transactions/inner/liquidated_position.py
ddx/common/transactions/inner/liquidation_entry.py
ddx/common/transactions/inner/liquidation_fill.py
ddx/common/transactions/inner/outcome.py
ddx/common/transactions/inner/trade_fill.py
ddx/common/transactions/insurance_fund_update.py
ddx/common/transactions/insurance_fund_withdraw.py
ddx/common/transactions/liquidation.py
ddx/common/transactions/partial_fill.py
ddx/common/transactions/pnl_realization.py
ddx/common/transactions/post.py
ddx/common/transactions/post_order.py
ddx_python-1.1.0.dist-info/METADATA
ddx_python-1.1.0.dist-info/WHEEL
ddx_python-1.1.0.dist-info/RECORD
