Metadata-Version: 2.4
Name: ddx-python
Version: 1.1.0
Classifier: Development Status :: 4 - Beta
Classifier: Intended Audience :: Developers
Classifier: Topic :: Office/Business :: Financial :: Investment
Classifier: Topic :: Software Development :: Libraries :: Python Modules
Classifier: Programming Language :: Rust
Classifier: Programming Language :: Python :: Implementation :: CPython
Classifier: Programming Language :: Python :: 3.10
Classifier: Programming Language :: Python :: 3.11
Classifier: Programming Language :: Python :: 3.12
Classifier: Programming Language :: Python :: 3 :: Only
Classifier: Operating System :: POSIX :: Linux
Requires-Dist: maturin>=1.5.0,<1.6.0
Requires-Dist: pydantic>=2.0
Requires-Dist: websockets>=12.0,<13
Requires-Dist: 0x-contract-wrappers>=2.0.0,<3
Requires-Dist: aiohttp>=3.10.3,<4
Requires-Dist: asyncpg>=0.30.0,<1
Requires-Dist: attrs>=24.2.0,<25
Requires-Dist: cattrs>=23.2.3,<24
Requires-Dist: coloredlogs>=15.0.1,<16
Requires-Dist: configargparse>=1.7,<2
Requires-Dist: numpy>=2.2.6,<3
Requires-Dist: pandas>=2.2.2,<3
Requires-Dist: path>=17.0.0,<18
Requires-Dist: pathlib>=1.0.1,<2
Requires-Dist: plotly>=5.23.0,<6
Requires-Dist: psutil>=6.0.0,<7
Requires-Dist: requests>=2.32.3,<3
Requires-Dist: simplejson>=3.19.2,<4
Requires-Dist: sphinx>=8.0.2,<9
Requires-Dist: verboselogs>=1.7,<2
Requires-Dist: btrees>=6.0,<7
Requires-Dist: ccxt>=4.3.79,<5
Requires-Dist: coincurve>=20.0.0,<21
Requires-Dist: dash-bootstrap-components>=1.6.0,<2
Requires-Dist: python-dotenv>=1.0.1,<2
Requires-Dist: sexpdata>=1.0.2,<2
Requires-Dist: web3>=6.20.1,<7
Requires-Dist: werkzeug>=3.0.3,<4
Requires-Dist: gevent>=24.2.1,<25
Requires-Dist: sortedcontainers>=2.4.0,<3
Requires-Dist: aioresponses>=0.7.6,<0.8
Requires-Dist: colorama>=0.4.6,<0.5
Requires-Dist: loguru
Requires-Dist: black>=24.4.2,<25 ; extra == 'dev'
Requires-Dist: basedpyright ; extra == 'dev'
Requires-Dist: pipdeptree ; extra == 'dev'
Requires-Dist: jupyter-book>=0.6.5,<0.7 ; extra == 'notebook'
Requires-Dist: jupyter-dash>=0.4.2,<0.5 ; extra == 'notebook'
Requires-Dist: jupyterlab-lsp>=5.1.0,<6 ; extra == 'notebook'
Requires-Dist: jupyter>=1.0.0,<2 ; extra == 'notebook'
Requires-Dist: jupyterlab ; extra == 'notebook'
Requires-Dist: matplotlib>=3.9.1,<4 ; extra == 'notebook'
Requires-Dist: pytest>=8.3.5,<9 ; extra == 'test'
Requires-Dist: pytest-asyncio>=0.26.0,<0.27 ; extra == 'test'
Requires-Dist: pytest-pretty>=1.2.0,<2 ; extra == 'test'
Provides-Extra: dev
Provides-Extra: notebook
Provides-Extra: test
Requires-Python: >=3.10
